mkDocsOnFilesHandler/__init__.py
mkDocsOnFilesHandler/main.py
mkDocsOnFilesHandler-0.0.1.dist-info/METADATA
mkDocsOnFilesHandler-0.0.1.dist-info/WHEEL
mkDocsOnFilesHandler-0.0.1.dist-info/entry_points.txt
mkDocsOnFilesHandler-0.0.1.dist-info/top_level.txt
mkDocsOnFilesHandler-0.0.1.dist-info/RECORD
